venusai/__init__.py
venusai-1.28.3.dist-info/METADATA
venusai-1.28.3.dist-info/WHEEL
venusai-1.28.3.dist-info/top_level.txt
venusai-1.28.3.dist-info/RECORD
