Metadata-Version: 2.4
Name: venusai
Version: 1.28.3
Summary: Install `venai` instead of this package.
Author: Mert Sirakaya
Classifier: Programming Language :: Python :: 3
Classifier: License :: OSI Approved :: MIT License
Classifier: Operating System :: OS Independent
Requires-Dist: venai<=1.28.3
Dynamic: author
Dynamic: classifier
Dynamic: requires-dist
Dynamic: summary
